autodoc_ai/ast_handler.py
autodoc_ai/cli.py
autodoc_ai/config.py
autodoc_ai/formatters.py
autodoc_ai/generators.py
autodoc_ai/json_output.py
autodoc_ai/llm_services.py
autodoc_ai/parser.py
autodoc_ai/transformers.py
autodoc_ai/utils.py
autodoc_ai/processors/__init__.py
autodoc_ai/processors/base.py
autodoc_ai/processors/dead_code_processor.py
autodoc_ai/processors/docstring_processor.py
autodoc_ai/processors/magic_number_processor.py
autodoc_ai/processors/type_hint_processor.py
zenco-1.3.1.dist-info/licenses/LICENSE
zenco-1.3.1.dist-info/METADATA
zenco-1.3.1.dist-info/WHEEL
zenco-1.3.1.dist-info/entry_points.txt
zenco-1.3.1.dist-info/top_level.txt
zenco-1.3.1.dist-info/RECORD
