Metadata-Version: 2.4
Name: zenco
Version: 1.3.1
Summary: AI-powered code analysis and enhancement tool with multi-language support for docstrings, type hints, magic numbers, and dead code detection.
Author-email: Nirajan Paudel <nirajanpaudel33@gmail.com>
License: MIT
Project-URL: Homepage, https://github.com/paudelnirajan/zenco
Project-URL: Repository, https://github.com/paudelnirajan/zenco
Project-URL: Documentation, https://github.com/paudelnirajan/zenco#readme
Project-URL: Bug Tracker, https://github.com/paudelnirajan/zenco/issues
Keywords: ai,code-analysis,documentation,refactoring,type-hints,dead-code,python,javascript,java,cpp,go
Classifier: Development Status :: 5 - Production/Stable
Classifier: Intended Audience :: Developers
Classifier: Topic :: Software Development :: Code Generators
Classifier: Topic :: Software Development :: Documentation
Classifier: Topic :: Software Development :: Quality Assurance
Classifier: Programming Language :: Python :: 3
Classifier: Programming Language :: Python :: 3.9
Classifier: Programming Language :: Python :: 3.10
Classifier: Programming Language :: Python :: 3.11
Classifier: Programming Language :: Python :: 3.12
Classifier: License :: OSI Approved :: MIT License
Classifier: Operating System :: OS Independent
Requires-Python: >=3.9
License-File: LICENSE
Requires-Dist: groq>=0.4.0
Requires-Dist: openai>=1.0.0
Requires-Dist: anthropic>=0.7.0
Requires-Dist: google-generativeai>=0.3.0
Requires-Dist: python-dotenv>=1.0.0
Requires-Dist: pathspec>=0.11.0
Requires-Dist: GitPython>=3.1.0
Requires-Dist: tree-sitter>=0.20.0
Requires-Dist: tree-sitter-python>=0.20.0
Requires-Dist: tree-sitter-javascript>=0.20.0
Requires-Dist: tree-sitter-java>=0.20.0
Requires-Dist: tree-sitter-go>=0.20.0
Requires-Dist: tree-sitter-cpp>=0.20.0
Requires-Dist: rich>=13.0.0
Requires-Dist: colorama>=0.4.6
Requires-Dist: tomli; python_version < "3.11"
Dynamic: license-file
